{
    "zinq" : [
        {
            "name" : "fractal_generator",
            "options" : {
                "category" : {
                    "orbit" : {
                        "fractal" : {
                            "mandelbrot" : {}
                        },
                        "algorithm" : {
                            "escape" : {}
                        },
                        "coloring" : {
                            "periodic" : {}
                        },
                        "center" : {
                            "re" : -0.75, "im" : 0
                        },
                        "zoom" : 1.2
                    }
                }
            }
        }
    ]
}
